Metadata-Version: 2.1
Name: jraph
Version: 0.0.6.dev0
Summary: Jraph: A library for Graph Neural Networks in Jax
Home-page: https://github.com/deepmind/jraph
Author: DeepMind
Author-email: jax_graph_nets@google.com
License: Apache 2.0
Keywords: jax graph neural networks python machine learning
Classifier: Development Status :: 5 - Production/Stable
Classifier: Environment :: Console
Classifier: Intended Audience :: Science/Research
Classifier: Intended Audience :: Developers
Classifier: License :: OSI Approved :: Apache Software License
Classifier: Operating System :: OS Independent
Classifier: Programming Language :: Python
Classifier: Programming Language :: Python :: 3
Classifier: Topic :: Scientific/Engineering :: Artificial Intelligence
Classifier: Topic :: Software Development :: Libraries :: Python Modules
Requires-Python: >=3.6
License-File: LICENSE
Requires-Dist: jax (>=0.1.55)
Requires-Dist: jaxlib (>=0.1.37)
Requires-Dist: numpy (>=1.18.0)
Provides-Extra: examples
Requires-Dist: dm-haiku (>=0.0.2) ; extra == 'examples'
Requires-Dist: absl-py (>=0.9) ; extra == 'examples'
Requires-Dist: frozendict (>=2.0.2) ; extra == 'examples'
Requires-Dist: optax (>=0.0.1) ; extra == 'examples'
Requires-Dist: scipy (>=1.2.1) ; extra == 'examples'
Provides-Extra: ogb_examples
Requires-Dist: dm-haiku (>=0.0.2) ; extra == 'ogb_examples'
Requires-Dist: absl-py (>=0.9) ; extra == 'ogb_examples'
Requires-Dist: optax (>=0.0.1) ; extra == 'ogb_examples'
Requires-Dist: pandas (>=1.0.5) ; extra == 'ogb_examples'
Requires-Dist: dm-tree (>=0.1.5) ; extra == 'ogb_examples'
